test/__init__.py
test/test_current_weather.py
test/test_daily_weather.py
weatherkit/__init__.py
weatherkit/current_weather.py
weatherkit/daily_weather.py
weatherkit-1.1.1.dist-info/AUTHORS.md
weatherkit-1.1.1.dist-info/LICENSE
weatherkit-1.1.1.dist-info/METADATA
weatherkit-1.1.1.dist-info/WHEEL
weatherkit-1.1.1.dist-info/top_level.txt
weatherkit-1.1.1.dist-info/RECORD
