Metadata-Version: 2.1
Name: weatherkit
Version: 1.1.1
Summary: Get weather details of any city or latitude and longitude of the location. without an API key.
Home-page: https://github.com/suvanbanerjee/weatherkit
Author: Suvan Banerjee
Author-email: <banerjeesuvan@gmail.com>
Keywords: python,weather,weatherkit,openweatherapi
Classifier: Development Status :: 4 - Beta
Classifier: Intended Audience :: Developers
Classifier: Programming Language :: Python :: 3
Classifier: License :: OSI Approved :: MIT License
Classifier: Operating System :: OS Independent
Requires-Python: >=3.5
License-File: LICENSE
License-File: AUTHORS.md
Requires-Dist: geopy
